MANIFEST.in
README
README.rst
setup.py
django_smartagent.egg-info/PKG-INFO
django_smartagent.egg-info/SOURCES.txt
django_smartagent.egg-info/dependency_links.txt
django_smartagent.egg-info/not-zip-safe
django_smartagent.egg-info/top_level.txt
smartagent/__init__.py
smartagent/agents_basic.pkl
smartagent/decorators.py
smartagent/middleware.py
smartagent/models.py
smartagent/tests.py
smartagent/urls.py
smartagent/utils.py
smartagent/views.py