Metadata-Version: 1.0
Name: django-smartagent
Version: 0.1.1
Summary: django-smartagent is the fastest and most complete user agent parser
Home-page: http://github.com/jamespacileo/django-smartagent/
Author: James Pacileo
Author-email: jamespacileo@gmail.com
License: BSD License
Keywords: django apps
Platform: UNKNOWN
Classifier: Environment :: Plugins
Classifier: Framework :: Django
Classifier: Intended Audience :: Developers
Classifier: License :: OSI Approved :: BSD License
Classifier: Programming Language :: Python
Classifier: Topic :: Software Development :: Libraries :: Python Modules
